<?xml version="1.0"?>
<opencv_storage>
<cascade>
  <stageType>BOOST</stageType>
  <featureType>HAAR</featureType>
  <height>40</height>
  <width>20</width>
  <stageParams>
    <boostType>GAB</boostType>
    <minHitRate>9.9900001287460327e-001</minHitRate>
    <maxFalseAlarm>5.0000000000000000e-001</maxFalseAlarm>
    <weightTrimRate>9.4999999999999996e-001</weightTrimRate>
    <maxDepth>1</maxDepth>
    <maxWeakCount>100</maxWeakCount></stageParams>
  <featureParams>
    <maxCatCount>0</maxCatCount>
    <featSize>1</featSize>
    <mode>ALL</mode></featureParams>
  <stageNum>12</stageNum>
  <stages>
    <!-- stage 0 -->
    <_>
      <maxWeakCount>1</maxWeakCount>
      <stageThreshold>1.</stageThreshold>
      <weakClassifiers>
        <_>
          <internalNodes>
            0 -1 3 -1.7715902067720890e-003</internalNodes>
          <leafValues>
            1. -1.</leafValues></_></weakClassifiers></_>
    <!-- stage 1 -->
    <_>
      <maxWeakCount>1</maxWeakCount>
      <stageThreshold>1.</stageThreshold>
      <weakClassifiers>
        <_>
          <internalNodes>
            0 -1 2 -3.2151603698730469e-001</internalNodes>
          <leafValues>
            1. -1.</leafValues></_></weakClassifiers></_>
    <!-- stage 2 -->
    <_>
      <maxWeakCount>1</maxWeakCount>
      <stageThreshold>1.</stageThreshold>
      <weakClassifiers>
        <_>
          <internalNodes>
            0 -1 1 8.5984356701374054e-007</internalNodes>
          <leafValues>
            -1. 1.</leafValues></_></weakClassifiers></_>
    <!-- stage 3 -->
    <_>
      <maxWeakCount>1</maxWeakCount>
      <stageThreshold>1.</stageThreshold>
      <weakClassifiers>
        <_>
          <internalNodes>
            0 -1 8 1.9272286444902420e-002</internalNodes>
          <leafValues>
            -1. 1.</leafValues></_></weakClassifiers></_>
    <!-- stage 4 -->
    <_>
      <maxWeakCount>1</maxWeakCount>
      <stageThreshold>1.</stageThreshold>
      <weakClassifiers>
        <_>
          <internalNodes>
            0 -1 4 -1.9667717814445496e-001</internalNodes>
          <leafValues>
            1. -1.</leafValues></_></weakClassifiers></_>
    <!-- stage 5 -->
    <_>
      <maxWeakCount>1</maxWeakCount>
      <stageThreshold>1.</stageThreshold>
      <weakClassifiers>
        <_>
          <internalNodes>
            0 -1 5 -2.7367983013391495e-002</internalNodes>
          <leafValues>
            -1. 1.</leafValues></_></weakClassifiers></_>
    <!-- stage 6 -->
    <_>
      <maxWeakCount>1</maxWeakCount>
      <stageThreshold>1.</stageThreshold>
      <weakClassifiers>
        <_>
          <internalNodes>
            0 -1 6 5.1103988662362099e-003</internalNodes>
          <leafValues>
            1. -1.</leafValues></_></weakClassifiers></_>
    <!-- stage 7 -->
    <_>
      <maxWeakCount>1</maxWeakCount>
      <stageThreshold>1.</stageThreshold>
      <weakClassifiers>
        <_>
          <internalNodes>
            0 -1 11 -8.1934615969657898e-002</internalNodes>
          <leafValues>
            1. -1.</leafValues></_></weakClassifiers></_>
    <!-- stage 8 -->
    <_>
      <maxWeakCount>1</maxWeakCount>
      <stageThreshold>1.</stageThreshold>
      <weakClassifiers>
        <_>
          <internalNodes>
            0 -1 10 -1.3636076450347900e-001</internalNodes>
          <leafValues>
            1. -1.</leafValues></_></weakClassifiers></_>
    <!-- stage 9 -->
    <_>
      <maxWeakCount>1</maxWeakCount>
      <stageThreshold>1.</stageThreshold>
      <weakClassifiers>
        <_>
          <internalNodes>
            0 -1 0 1.4969180338084698e-003</internalNodes>
          <leafValues>
            1. -1.</leafValues></_></weakClassifiers></_>
    <!-- stage 10 -->
    <_>
      <maxWeakCount>1</maxWeakCount>
      <stageThreshold>1.</stageThreshold>
      <weakClassifiers>
        <_>
          <internalNodes>
            0 -1 9 -1.6249770123977214e-004</internalNodes>
          <leafValues>
            -1. 1.</leafValues></_></weakClassifiers></_>
    <!-- stage 11 -->
    <_>
      <maxWeakCount>1</maxWeakCount>
      <stageThreshold>1.</stageThreshold>
      <weakClassifiers>
        <_>
          <internalNodes>
            0 -1 7 -3.0723285675048828e-001</internalNodes>
          <leafValues>
            -1. 1.</leafValues></_></weakClassifiers></_></stages>
  <features>
    <_>
      <rects>
        <_>
          0 0 1 20 -1.</_>
        <_>
          0 10 1 10 2.</_></rects>
      <tilted>0</tilted></_>
    <_>
      <rects>
        <_>
          0 0 1 30 -1.</_>
        <_>
          0 10 1 10 3.</_></rects>
      <tilted>0</tilted></_>
    <_>
      <rects>
        <_>
          0 0 9 39 -1.</_>
        <_>
          3 13 3 13 9.</_></rects>
      <tilted>0</tilted></_>
    <_>
      <rects>
        <_>
          0 0 16 11 -1.</_>
        <_>
          4 0 8 11 2.</_></rects>
      <tilted>0</tilted></_>
    <_>
      <rects>
        <_>
          0 0 20 31 -1.</_>
        <_>
          5 0 10 31 2.</_></rects>
      <tilted>0</tilted></_>
    <_>
      <rects>
        <_>
          0 0 18 9 -1.</_>
        <_>
          6 3 6 3 9.</_></rects>
      <tilted>0</tilted></_>
    <_>
      <rects>
        <_>
          0 0 8 6 -1.</_>
        <_>
          0 3 8 3 2.</_></rects>
      <tilted>0</tilted></_>
    <_>
      <rects>
        <_>
          0 0 10 36 -1.</_>
        <_>
          0 9 10 18 2.</_></rects>
      <tilted>0</tilted></_>
    <_>
      <rects>
        <_>
          0 0 19 12 -1.</_>
        <_>
          0 3 19 6 2.</_></rects>
      <tilted>0</tilted></_>
    <_>
      <rects>
        <_>
          0 2 6 6 -1.</_>
        <_>
          0 4 6 2 3.</_></rects>
      <tilted>0</tilted></_>
    <_>
      <rects>
        <_>
          0 4 10 36 -1.</_>
        <_>
          5 4 5 36 2.</_></rects>
      <tilted>0</tilted></_>
    <_>
      <rects>
        <_>
          0 14 6 16 -1.</_>
        <_>
          0 18 6 8 2.</_></rects>
      <tilted>0</tilted></_></features></cascade>
</opencv_storage>
